test_mcp_tcl/__init__.py
test_mcp_tcl/server.py
test_mcp_tcl-0.1.0.dist-info/METADATA
test_mcp_tcl-0.1.0.dist-info/WHEEL
test_mcp_tcl-0.1.0.dist-info/entry_points.txt
test_mcp_tcl-0.1.0.dist-info/RECORD
