Metadata-Version: 2.4
Name: test-mcp-tcl
Version: 0.1.0
Summary: test create mcp server
Author-email: "chuanwen.peng" <chuanwen.peng@tcl.com>
Requires-Python: >=3.11
Requires-Dist: mcp>=1.10.1
